LICENSE
MANIFEST.in
NOTICE
README.rst
setup.py
django_bootstrap_staticfiles/__init__.py
django_bootstrap_staticfiles/models.py
django_bootstrap_staticfiles.egg-info/PKG-INFO
django_bootstrap_staticfiles.egg-info/SOURCES.txt
django_bootstrap_staticfiles.egg-info/dependency_links.txt
django_bootstrap_staticfiles.egg-info/top_level.txt
django_bootstrap_staticfiles/static/css/bootstrap-theme.css
django_bootstrap_staticfiles/static/css/bootstrap-theme.min.css
django_bootstrap_staticfiles/static/css/bootstrap.css
django_bootstrap_staticfiles/static/css/bootstrap.min.css
django_bootstrap_staticfiles/static/fonts/glyphicons-halflings-regular.eot
django_bootstrap_staticfiles/static/fonts/glyphicons-halflings-regular.svg
django_bootstrap_staticfiles/static/fonts/glyphicons-halflings-regular.ttf
django_bootstrap_staticfiles/static/fonts/glyphicons-halflings-regular.woff
django_bootstrap_staticfiles/static/js/bootstrap.js
django_bootstrap_staticfiles/static/js/bootstrap.min.js