Metadata-Version: 1.1
Name: django-bootstrap-staticfiles
Version: 3.0.0.1
Summary: Django app that provides compiled Bootstrap assets
Home-page: https://github.com/55minutes/django-bootstrap-staticfiles
Author: George Song
Author-email: george@55minutes.com
License: MIT
Download-URL: http://pypi.python.org/pypi/django-bootstrap-staticfiles
Keywords: django app staticfiles twitter bootstrap
Platform: UNKNOWN
Classifier: Development Status :: 5 - Production/Stable
Classifier: Environment :: Web Environment
Classifier: Framework :: Django
Classifier: Intended Audience :: Developers
Classifier: License :: OSI Approved :: Apache Software License
Classifier: Programming Language :: Python
Classifier: Programming Language :: Python :: 2.7
Classifier: Topic :: Software Development :: Libraries
